{
  "now": "2021-08-18T16:12:47.000Z",
  "program": "ZVView, ver. 2020-01-30",
  "file": "Copy of plotted data",
  "f":"y(x)",
  "title": "Ruthenium",
  "title2": "at Ne = 1.0E+21 cm-3",
  "xAxis": "Charge State",
  "yAxis": "Charge Fraction",
  "xUnits": "",
  "yUnits": "",
  "xMin": -2.2,
  "xMax": 46.2,
  "funcs": [
    {
      "ifunc":0,
      "fName":"Te =      0.5 eV",
      "lx":45,
      "i0x":0,
      "i1x":44,
      "pts":[
	 {"x":0,	"y":0.99689}
	,{"x":1,	"y":0.0031075}
	,{"x":2,	"y":4.6721e-13}
	,{"x":3,	"y":2.6965e-32}
	,{"x":4,	"y":0}
	,{"x":5,	"y":0}
	,{"x":6,	"y":0}
	,{"x":7,	"y":0}
	,{"x":8,	"y":0}
	,{"x":9,	"y":0}
	,{"x":10,	"y":0}
	,{"x":11,	"y":0}
	,{"x":12,	"y":0}
	,{"x":13,	"y":0}
	,{"x":14,	"y":0}
	,{"x":15,	"y":0}
	,{"x":16,	"y":0}
	,{"x":17,	"y":0}
	,{"x":18,	"y":0}
	,{"x":19,	"y":0}
	,{"x":20,	"y":0}
	,{"x":21,	"y":0}
	,{"x":22,	"y":0}
	,{"x":23,	"y":0}
	,{"x":24,	"y":0}
	,{"x":25,	"y":0}
	,{"x":26,	"y":0}
	,{"x":27,	"y":0}
	,{"x":28,	"y":0}
	,{"x":29,	"y":0}
	,{"x":30,	"y":0}
	,{"x":31,	"y":0}
	,{"x":32,	"y":0}
	,{"x":33,	"y":0}
	,{"x":34,	"y":0}
	,{"x":35,	"y":0}
	,{"x":36,	"y":0}
	,{"x":37,	"y":0}
	,{"x":38,	"y":0}
	,{"x":39,	"y":0}
	,{"x":40,	"y":0}
	,{"x":41,	"y":0}
	,{"x":42,	"y":0}
	,{"x":43,	"y":0}
	,{"x":44,	"y":0}
      ]
    }
    ,{
      "ifunc":1,
      "fName":"Te =      1.0 eV",
      "lx":45,
      "i0x":0,
      "i1x":44,
      "pts":[
	 {"x":0,	"y":0.95272}
	,{"x":1,	"y":0.047274}
	,{"x":2,	"y":1.7689e-6}
	,{"x":3,	"y":1.2115e-15}
	,{"x":4,	"y":2.5517e-30}
	,{"x":5,	"y":0}
	,{"x":6,	"y":0}
	,{"x":7,	"y":0}
	,{"x":8,	"y":0}
	,{"x":9,	"y":0}
	,{"x":10,	"y":0}
	,{"x":11,	"y":0}
	,{"x":12,	"y":0}
	,{"x":13,	"y":0}
	,{"x":14,	"y":0}
	,{"x":15,	"y":0}
	,{"x":16,	"y":0}
	,{"x":17,	"y":0}
	,{"x":18,	"y":0}
	,{"x":19,	"y":0}
	,{"x":20,	"y":0}
	,{"x":21,	"y":0}
	,{"x":22,	"y":0}
	,{"x":23,	"y":0}
	,{"x":24,	"y":0}
	,{"x":25,	"y":0}
	,{"x":26,	"y":0}
	,{"x":27,	"y":0}
	,{"x":28,	"y":0}
	,{"x":29,	"y":0}
	,{"x":30,	"y":0}
	,{"x":31,	"y":0}
	,{"x":32,	"y":0}
	,{"x":33,	"y":0}
	,{"x":34,	"y":0}
	,{"x":35,	"y":0}
	,{"x":36,	"y":0}
	,{"x":37,	"y":0}
	,{"x":38,	"y":0}
	,{"x":39,	"y":0}
	,{"x":40,	"y":0}
	,{"x":41,	"y":0}
	,{"x":42,	"y":0}
	,{"x":43,	"y":0}
	,{"x":44,	"y":0}
      ]
    }
    ,{
      "ifunc":2,
      "fName":"Te =      1.5 eV",
      "lx":45,
      "i0x":0,
      "i1x":44,
      "pts":[
	 {"x":0,	"y":0.91405}
	,{"x":1,	"y":0.085692}
	,{"x":2,	"y":0.00025681}
	,{"x":3,	"y":5.3177e-10}
	,{"x":4,	"y":2.2219e-19}
	,{"x":5,	"y":8.2784e-33}
	,{"x":6,	"y":0}
	,{"x":7,	"y":0}
	,{"x":8,	"y":0}
	,{"x":9,	"y":0}
	,{"x":10,	"y":0}
	,{"x":11,	"y":0}
	,{"x":12,	"y":0}
	,{"x":13,	"y":0}
	,{"x":14,	"y":0}
	,{"x":15,	"y":0}
	,{"x":16,	"y":0}
	,{"x":17,	"y":0}
	,{"x":18,	"y":0}
	,{"x":19,	"y":0}
	,{"x":20,	"y":0}
	,{"x":21,	"y":0}
	,{"x":22,	"y":0}
	,{"x":23,	"y":0}
	,{"x":24,	"y":0}
	,{"x":25,	"y":0}
	,{"x":26,	"y":0}
	,{"x":27,	"y":0}
	,{"x":28,	"y":0}
	,{"x":29,	"y":0}
	,{"x":30,	"y":0}
	,{"x":31,	"y":0}
	,{"x":32,	"y":0}
	,{"x":33,	"y":0}
	,{"x":34,	"y":0}
	,{"x":35,	"y":0}
	,{"x":36,	"y":0}
	,{"x":37,	"y":0}
	,{"x":38,	"y":0}
	,{"x":39,	"y":0}
	,{"x":40,	"y":0}
	,{"x":41,	"y":0}
	,{"x":42,	"y":0}
	,{"x":43,	"y":0}
	,{"x":44,	"y":0}
      ]
    }
    ,{
      "ifunc":3,
      "fName":"Te =      2.0 eV",
      "lx":45,
      "i0x":0,
      "i1x":44,
      "pts":[
	 {"x":0,	"y":0.90454}
	,{"x":1,	"y":0.09303}
	,{"x":2,	"y":0.002428}
	,{"x":3,	"y":3.1451e-7}
	,{"x":4,	"y":6.672e-14}
	,{"x":5,	"y":1.2533e-23}
	,{"x":6,	"y":1.2046e-36}
	,{"x":7,	"y":0}
	,{"x":8,	"y":0}
	,{"x":9,	"y":0}
	,{"x":10,	"y":0}
	,{"x":11,	"y":0}
	,{"x":12,	"y":0}
	,{"x":13,	"y":0}
	,{"x":14,	"y":0}
	,{"x":15,	"y":0}
	,{"x":16,	"y":0}
	,{"x":17,	"y":0}
	,{"x":18,	"y":0}
	,{"x":19,	"y":0}
	,{"x":20,	"y":0}
	,{"x":21,	"y":0}
	,{"x":22,	"y":0}
	,{"x":23,	"y":0}
	,{"x":24,	"y":0}
	,{"x":25,	"y":0}
	,{"x":26,	"y":0}
	,{"x":27,	"y":0}
	,{"x":28,	"y":0}
	,{"x":29,	"y":0}
	,{"x":30,	"y":0}
	,{"x":31,	"y":0}
	,{"x":32,	"y":0}
	,{"x":33,	"y":0}
	,{"x":34,	"y":0}
	,{"x":35,	"y":0}
	,{"x":36,	"y":0}
	,{"x":37,	"y":0}
	,{"x":38,	"y":0}
	,{"x":39,	"y":0}
	,{"x":40,	"y":0}
	,{"x":41,	"y":0}
	,{"x":42,	"y":0}
	,{"x":43,	"y":0}
	,{"x":44,	"y":0}
      ]
    }
    ,{
      "ifunc":4,
      "fName":"Te =      5.0 eV",
      "lx":45,
      "i0x":0,
      "i1x":44,
      "pts":[
	 {"x":0,	"y":0.45859}
	,{"x":1,	"y":0.35672}
	,{"x":2,	"y":0.14931}
	,{"x":3,	"y":0.034394}
	,{"x":4,	"y":0.00098869}
	,{"x":5,	"y":1.7853e-6}
	,{"x":6,	"y":1.4541e-10}
	,{"x":7,	"y":3.7529e-16}
	,{"x":8,	"y":2.7748e-23}
	,{"x":9,	"y":2.9329e-36}
	,{"x":10,	"y":0}
	,{"x":11,	"y":0}
	,{"x":12,	"y":0}
	,{"x":13,	"y":0}
	,{"x":14,	"y":0}
	,{"x":15,	"y":0}
	,{"x":16,	"y":0}
	,{"x":17,	"y":0}
	,{"x":18,	"y":0}
	,{"x":19,	"y":0}
	,{"x":20,	"y":0}
	,{"x":21,	"y":0}
	,{"x":22,	"y":0}
	,{"x":23,	"y":0}
	,{"x":24,	"y":0}
	,{"x":25,	"y":0}
	,{"x":26,	"y":0}
	,{"x":27,	"y":0}
	,{"x":28,	"y":0}
	,{"x":29,	"y":0}
	,{"x":30,	"y":0}
	,{"x":31,	"y":0}
	,{"x":32,	"y":0}
	,{"x":33,	"y":0}
	,{"x":34,	"y":0}
	,{"x":35,	"y":0}
	,{"x":36,	"y":0}
	,{"x":37,	"y":0}
	,{"x":38,	"y":0}
	,{"x":39,	"y":0}
	,{"x":40,	"y":0}
	,{"x":41,	"y":0}
	,{"x":42,	"y":0}
	,{"x":43,	"y":0}
	,{"x":44,	"y":0}
      ]
    }
    ,{
      "ifunc":5,
      "fName":"Te =      7.0 eV",
      "lx":45,
      "i0x":0,
      "i1x":44,
      "pts":[
	 {"x":0,	"y":0.052447}
	,{"x":1,	"y":0.26462}
	,{"x":2,	"y":0.35413}
	,{"x":3,	"y":0.2646}
	,{"x":4,	"y":0.06134}
	,{"x":5,	"y":0.0028495}
	,{"x":6,	"y":1.5373e-5}
	,{"x":7,	"y":6.9834e-9}
	,{"x":8,	"y":2.4174e-13}
	,{"x":9,	"y":5.3484e-22}
	,{"x":10,	"y":5.3052e-32}
	,{"x":11,	"y":2.14399e-43}
	,{"x":12,	"y":0}
	,{"x":13,	"y":0}
	,{"x":14,	"y":0}
	,{"x":15,	"y":0}
	,{"x":16,	"y":0}
	,{"x":17,	"y":0}
	,{"x":18,	"y":0}
	,{"x":19,	"y":0}
	,{"x":20,	"y":0}
	,{"x":21,	"y":0}
	,{"x":22,	"y":0}
	,{"x":23,	"y":0}
	,{"x":24,	"y":0}
	,{"x":25,	"y":0}
	,{"x":26,	"y":0}
	,{"x":27,	"y":0}
	,{"x":28,	"y":0}
	,{"x":29,	"y":0}
	,{"x":30,	"y":0}
	,{"x":31,	"y":0}
	,{"x":32,	"y":0}
	,{"x":33,	"y":0}
	,{"x":34,	"y":0}
	,{"x":35,	"y":0}
	,{"x":36,	"y":0}
	,{"x":37,	"y":0}
	,{"x":38,	"y":0}
	,{"x":39,	"y":0}
	,{"x":40,	"y":0}
	,{"x":41,	"y":0}
	,{"x":42,	"y":0}
	,{"x":43,	"y":0}
	,{"x":44,	"y":0}
      ]
    }
    ,{
      "ifunc":6,
      "fName":"Te =     10.0 eV",
      "lx":45,
      "i0x":0,
      "i1x":44,
      "pts":[
	 {"x":0,	"y":0.00097309}
	,{"x":1,	"y":0.018876}
	,{"x":2,	"y":0.12062}
	,{"x":3,	"y":0.37381}
	,{"x":4,	"y":0.32998}
	,{"x":5,	"y":0.13951}
	,{"x":6,	"y":0.015859}
	,{"x":7,	"y":0.00036861}
	,{"x":8,	"y":1.4079e-6}
	,{"x":9,	"y":6.1477e-12}
	,{"x":10,	"y":2.8973e-18}
	,{"x":11,	"y":1.3711e-25}
	,{"x":12,	"y":6.0057e-34}
	,{"x":13,	"y":1.33123e-43}
	,{"x":14,	"y":0}
	,{"x":15,	"y":0}
	,{"x":16,	"y":0}
	,{"x":17,	"y":0}
	,{"x":18,	"y":0}
	,{"x":19,	"y":0}
	,{"x":20,	"y":0}
	,{"x":21,	"y":0}
	,{"x":22,	"y":0}
	,{"x":23,	"y":0}
	,{"x":24,	"y":0}
	,{"x":25,	"y":0}
	,{"x":26,	"y":0}
	,{"x":27,	"y":0}
	,{"x":28,	"y":0}
	,{"x":29,	"y":0}
	,{"x":30,	"y":0}
	,{"x":31,	"y":0}
	,{"x":32,	"y":0}
	,{"x":33,	"y":0}
	,{"x":34,	"y":0}
	,{"x":35,	"y":0}
	,{"x":36,	"y":0}
	,{"x":37,	"y":0}
	,{"x":38,	"y":0}
	,{"x":39,	"y":0}
	,{"x":40,	"y":0}
	,{"x":41,	"y":0}
	,{"x":42,	"y":0}
	,{"x":43,	"y":0}
	,{"x":44,	"y":0}
      ]
    }
    ,{
      "ifunc":7,
      "fName":"Te =     15.0 eV",
      "lx":45,
      "i0x":0,
      "i1x":44,
      "pts":[
	 {"x":0,	"y":6.7274e-7}
	,{"x":1,	"y":4.5909e-5}
	,{"x":2,	"y":0.0013887}
	,{"x":3,	"y":0.025992}
	,{"x":4,	"y":0.13087}
	,{"x":5,	"y":0.35428}
	,{"x":6,	"y":0.33227}
	,{"x":7,	"y":0.13756}
	,{"x":8,	"y":0.017558}
	,{"x":9,	"y":3.3478e-5}
	,{"x":10,	"y":1.3686e-8}
	,{"x":11,	"y":1.1334e-12}
	,{"x":12,	"y":1.781e-17}
	,{"x":13,	"y":3.5009e-23}
	,{"x":14,	"y":1.0645e-29}
	,{"x":15,	"y":4.862e-38}
	,{"x":16,	"y":0}
	,{"x":17,	"y":0}
	,{"x":18,	"y":0}
	,{"x":19,	"y":0}
	,{"x":20,	"y":0}
	,{"x":21,	"y":0}
	,{"x":22,	"y":0}
	,{"x":23,	"y":0}
	,{"x":24,	"y":0}
	,{"x":25,	"y":0}
	,{"x":26,	"y":0}
	,{"x":27,	"y":0}
	,{"x":28,	"y":0}
	,{"x":29,	"y":0}
	,{"x":30,	"y":0}
	,{"x":31,	"y":0}
	,{"x":32,	"y":0}
	,{"x":33,	"y":0}
	,{"x":34,	"y":0}
	,{"x":35,	"y":0}
	,{"x":36,	"y":0}
	,{"x":37,	"y":0}
	,{"x":38,	"y":0}
	,{"x":39,	"y":0}
	,{"x":40,	"y":0}
	,{"x":41,	"y":0}
	,{"x":42,	"y":0}
	,{"x":43,	"y":0}
	,{"x":44,	"y":0}
      ]
    }
    ,{
      "ifunc":8,
      "fName":"Te =     23.0 eV",
      "lx":45,
      "i0x":0,
      "i1x":44,
      "pts":[
	 {"x":0,	"y":2.996e-11}
	,{"x":1,	"y":3.8135e-9}
	,{"x":2,	"y":4.3515e-7}
	,{"x":3,	"y":4.035e-5}
	,{"x":4,	"y":0.0012061}
	,{"x":5,	"y":0.02353}
	,{"x":6,	"y":0.15999}
	,{"x":7,	"y":0.3934}
	,{"x":8,	"y":0.36608}
	,{"x":9,	"y":0.052888}
	,{"x":10,	"y":0.0028086}
	,{"x":11,	"y":5.0127e-5}
	,{"x":12,	"y":2.8305e-7}
	,{"x":13,	"y":3.776e-10}
	,{"x":14,	"y":1.3175e-13}
	,{"x":15,	"y":2.527e-18}
	,{"x":16,	"y":7.2899e-24}
	,{"x":17,	"y":3.6791e-32}
	,{"x":18,	"y":7.03732e-42}
	,{"x":19,	"y":0}
	,{"x":20,	"y":0}
	,{"x":21,	"y":0}
	,{"x":22,	"y":0}
	,{"x":23,	"y":0}
	,{"x":24,	"y":0}
	,{"x":25,	"y":0}
	,{"x":26,	"y":0}
	,{"x":27,	"y":0}
	,{"x":28,	"y":0}
	,{"x":29,	"y":0}
	,{"x":30,	"y":0}
	,{"x":31,	"y":0}
	,{"x":32,	"y":0}
	,{"x":33,	"y":0}
	,{"x":34,	"y":0}
	,{"x":35,	"y":0}
	,{"x":36,	"y":0}
	,{"x":37,	"y":0}
	,{"x":38,	"y":0}
	,{"x":39,	"y":0}
	,{"x":40,	"y":0}
	,{"x":41,	"y":0}
	,{"x":42,	"y":0}
	,{"x":43,	"y":0}
	,{"x":44,	"y":0}
      ]
    }
    ,{
      "ifunc":9,
      "fName":"Te =     32.0 eV",
      "lx":45,
      "i0x":0,
      "i1x":44,
      "pts":[
	 {"x":0,	"y":2.4032e-15}
	,{"x":1,	"y":6.3463e-13}
	,{"x":2,	"y":2.6968e-10}
	,{"x":3,	"y":4.4314e-8}
	,{"x":4,	"y":4.1884e-6}
	,{"x":5,	"y":0.00030692}
	,{"x":6,	"y":0.0092757}
	,{"x":7,	"y":0.075289}
	,{"x":8,	"y":0.2582}
	,{"x":9,	"y":0.33842}
	,{"x":10,	"y":0.23607}
	,{"x":11,	"y":0.072372}
	,{"x":12,	"y":0.0096052}
	,{"x":13,	"y":0.00044322}
	,{"x":14,	"y":7.1118e-6}
	,{"x":15,	"y":1.2579e-8}
	,{"x":16,	"y":4.4105e-12}
	,{"x":17,	"y":1.0127e-16}
	,{"x":18,	"y":1.7081e-22}
	,{"x":19,	"y":2.5542e-29}
	,{"x":20,	"y":3.4544e-37}
	,{"x":21,	"y":0}
	,{"x":22,	"y":0}
	,{"x":23,	"y":0}
	,{"x":24,	"y":0}
	,{"x":25,	"y":0}
	,{"x":26,	"y":0}
	,{"x":27,	"y":0}
	,{"x":28,	"y":0}
	,{"x":29,	"y":0}
	,{"x":30,	"y":0}
	,{"x":31,	"y":0}
	,{"x":32,	"y":0}
	,{"x":33,	"y":0}
	,{"x":34,	"y":0}
	,{"x":35,	"y":0}
	,{"x":36,	"y":0}
	,{"x":37,	"y":0}
	,{"x":38,	"y":0}
	,{"x":39,	"y":0}
	,{"x":40,	"y":0}
	,{"x":41,	"y":0}
	,{"x":42,	"y":0}
	,{"x":43,	"y":0}
	,{"x":44,	"y":0}
      ]
    }
    ,{
      "ifunc":10,
      "fName":"Te =     52.0 eV",
      "lx":45,
      "i0x":0,
      "i1x":44,
      "pts":[
	 {"x":0,	"y":5.1689e-24}
	,{"x":1,	"y":3.5695e-21}
	,{"x":2,	"y":4.6797e-18}
	,{"x":3,	"y":2.6207e-15}
	,{"x":4,	"y":1.4451e-12}
	,{"x":5,	"y":3.5651e-10}
	,{"x":6,	"y":5.8949e-8}
	,{"x":7,	"y":3.525e-6}
	,{"x":8,	"y":0.00010039}
	,{"x":9,	"y":0.0015772}
	,{"x":10,	"y":0.016591}
	,{"x":11,	"y":0.087151}
	,{"x":12,	"y":0.24896}
	,{"x":13,	"y":0.37122}
	,{"x":14,	"y":0.23984}
	,{"x":15,	"y":0.032329}
	,{"x":16,	"y":0.0020678}
	,{"x":17,	"y":0.00015457}
	,{"x":18,	"y":1.9728e-6}
	,{"x":19,	"y":4.408e-9}
	,{"x":20,	"y":1.7155e-12}
	,{"x":21,	"y":1.1226e-16}
	,{"x":22,	"y":1.2001e-21}
	,{"x":23,	"y":1.73e-27}
	,{"x":24,	"y":3.629e-34}
	,{"x":25,	"y":1.06246e-41}
	,{"x":26,	"y":0}
	,{"x":27,	"y":0}
	,{"x":28,	"y":0}
	,{"x":29,	"y":0}
	,{"x":30,	"y":0}
	,{"x":31,	"y":0}
	,{"x":32,	"y":0}
	,{"x":33,	"y":0}
	,{"x":34,	"y":0}
	,{"x":35,	"y":0}
	,{"x":36,	"y":0}
	,{"x":37,	"y":0}
	,{"x":38,	"y":0}
	,{"x":39,	"y":0}
	,{"x":40,	"y":0}
	,{"x":41,	"y":0}
	,{"x":42,	"y":0}
	,{"x":43,	"y":0}
	,{"x":44,	"y":0}
      ]
    }
    ,{
      "ifunc":11,
      "fName":"Te =     74.0 eV",
      "lx":45,
      "i0x":0,
      "i1x":44,
      "pts":[
	 {"x":0,	"y":5.1826e-32}
	,{"x":1,	"y":1.1053e-28}
	,{"x":2,	"y":1.8182e-25}
	,{"x":3,	"y":2.2121e-22}
	,{"x":4,	"y":2.8882e-19}
	,{"x":5,	"y":1.8158e-16}
	,{"x":6,	"y":1.0965e-13}
	,{"x":7,	"y":1.826e-11}
	,{"x":8,	"y":2.0788e-9}
	,{"x":9,	"y":1.5301e-7}
	,{"x":10,	"y":7.9691e-6}
	,{"x":11,	"y":0.00022123}
	,{"x":12,	"y":0.003594}
	,{"x":13,	"y":0.032783}
	,{"x":14,	"y":0.098215}
	,{"x":15,	"y":0.1072}
	,{"x":16,	"y":0.2463}
	,{"x":17,	"y":0.32575}
	,{"x":18,	"y":0.16037}
	,{"x":19,	"y":0.024562}
	,{"x":20,	"y":0.00099445}
	,{"x":21,	"y":9.7228e-6}
	,{"x":22,	"y":2.2187e-8}
	,{"x":23,	"y":1.0219e-11}
	,{"x":24,	"y":1.0172e-15}
	,{"x":25,	"y":2.1477e-20}
	,{"x":26,	"y":1.4838e-25}
	,{"x":27,	"y":2.3422e-32}
	,{"x":28,	"y":8.8699e-40}
	,{"x":29,	"y":0}
	,{"x":30,	"y":0}
	,{"x":31,	"y":0}
	,{"x":32,	"y":0}
	,{"x":33,	"y":0}
	,{"x":34,	"y":0}
	,{"x":35,	"y":0}
	,{"x":36,	"y":0}
	,{"x":37,	"y":0}
	,{"x":38,	"y":0}
	,{"x":39,	"y":0}
	,{"x":40,	"y":0}
	,{"x":41,	"y":0}
	,{"x":42,	"y":0}
	,{"x":43,	"y":0}
	,{"x":44,	"y":0}
      ]
    }
    ,{
      "ifunc":12,
      "fName":"Te =    100.0 eV",
      "lx":45,
      "i0x":0,
      "i1x":44,
      "pts":[
	 {"x":0,	"y":1.4071e-40}
	,{"x":1,	"y":5.0566e-37}
	,{"x":2,	"y":1.4632e-33}
	,{"x":3,	"y":3.2575e-30}
	,{"x":4,	"y":8.219e-27}
	,{"x":5,	"y":1.0444e-23}
	,{"x":6,	"y":1.3594e-20}
	,{"x":7,	"y":5.8607e-18}
	,{"x":8,	"y":1.8295e-15}
	,{"x":9,	"y":4.1094e-13}
	,{"x":10,	"y":6.7173e-11}
	,{"x":11,	"y":6.0197e-9}
	,{"x":12,	"y":3.3105e-7}
	,{"x":13,	"y":1.0621e-5}
	,{"x":14,	"y":8.6553e-5}
	,{"x":15,	"y":0.00053477}
	,{"x":16,	"y":0.012261}
	,{"x":17,	"y":0.099088}
	,{"x":18,	"y":0.30116}
	,{"x":19,	"y":0.37493}
	,{"x":20,	"y":0.18083}
	,{"x":21,	"y":0.02958}
	,{"x":22,	"y":0.0014977}
	,{"x":23,	"y":2.0567e-5}
	,{"x":24,	"y":8.0435e-8}
	,{"x":25,	"y":8.867e-11}
	,{"x":26,	"y":3.9169e-14}
	,{"x":27,	"y":8.2319e-19}
	,{"x":28,	"y":5.3893e-24}
	,{"x":29,	"y":1.093e-29}
	,{"x":30,	"y":7.6469e-36}
	,{"x":31,	"y":1.07339e-42}
	,{"x":32,	"y":0}
	,{"x":33,	"y":0}
	,{"x":34,	"y":0}
	,{"x":35,	"y":0}
	,{"x":36,	"y":0}
	,{"x":37,	"y":0}
	,{"x":38,	"y":0}
	,{"x":39,	"y":0}
	,{"x":40,	"y":0}
	,{"x":41,	"y":0}
	,{"x":42,	"y":0}
	,{"x":43,	"y":0}
	,{"x":44,	"y":0}
      ]
    }
    ,{
      "ifunc":13,
      "fName":"Te =    165.0 eV",
      "lx":45,
      "i0x":0,
      "i1x":44,
      "pts":[
	 {"x":0,	"y":0}
	,{"x":1,	"y":0}
	,{"x":2,	"y":0}
	,{"x":3,	"y":9.65495e-43}
	,{"x":4,	"y":4.4797e-39}
	,{"x":5,	"y":2.1259e-35}
	,{"x":6,	"y":6.204e-32}
	,{"x":7,	"y":1.0951e-28}
	,{"x":8,	"y":1.1441e-25}
	,{"x":9,	"y":1.3179e-22}
	,{"x":10,	"y":7.6768e-20}
	,{"x":11,	"y":2.9934e-17}
	,{"x":12,	"y":7.5627e-15}
	,{"x":13,	"y":1.1659e-12}
	,{"x":14,	"y":4.3755e-11}
	,{"x":15,	"y":1.9594e-9}
	,{"x":16,	"y":5.5973e-7}
	,{"x":17,	"y":5.1183e-5}
	,{"x":18,	"y":0.00168}
	,{"x":19,	"y":0.021641}
	,{"x":20,	"y":0.12005}
	,{"x":21,	"y":0.30366}
	,{"x":22,	"y":0.34829}
	,{"x":23,	"y":0.16834}
	,{"x":24,	"y":0.033521}
	,{"x":25,	"y":0.0026755}
	,{"x":26,	"y":9.4081e-5}
	,{"x":27,	"y":3.9346e-7}
	,{"x":28,	"y":7.1728e-10}
	,{"x":29,	"y":5.7405e-13}
	,{"x":30,	"y":2.137e-16}
	,{"x":31,	"y":2.638e-20}
	,{"x":32,	"y":1.6828e-24}
	,{"x":33,	"y":2.7681e-29}
	,{"x":34,	"y":2.2969e-34}
	,{"x":35,	"y":0}
	,{"x":36,	"y":0}
	,{"x":37,	"y":0}
	,{"x":38,	"y":0}
	,{"x":39,	"y":0}
	,{"x":40,	"y":0}
	,{"x":41,	"y":0}
	,{"x":42,	"y":0}
	,{"x":43,	"y":0}
	,{"x":44,	"y":0}
      ]
    }
    ,{
      "ifunc":14,
      "fName":"Te =    235.0 eV",
      "lx":45,
      "i0x":0,
      "i1x":44,
      "pts":[
	 {"x":0,	"y":0}
	,{"x":1,	"y":0}
	,{"x":2,	"y":0}
	,{"x":3,	"y":0}
	,{"x":4,	"y":0}
	,{"x":5,	"y":3.3491e-43}
	,{"x":6,	"y":1.7729e-39}
	,{"x":7,	"y":6.4853e-36}
	,{"x":8,	"y":1.3453e-32}
	,{"x":9,	"y":3.3601e-29}
	,{"x":10,	"y":4.1591e-26}
	,{"x":11,	"y":3.5173e-23}
	,{"x":12,	"y":1.9913e-20}
	,{"x":13,	"y":7.0518e-18}
	,{"x":14,	"y":6.7495e-16}
	,{"x":15,	"y":7.49e-14}
	,{"x":16,	"y":7.3354e-11}
	,{"x":17,	"y":2.3731e-8}
	,{"x":18,	"y":2.8619e-6}
	,{"x":19,	"y":0.00013856}
	,{"x":20,	"y":0.002904}
	,{"x":21,	"y":0.027778}
	,{"x":22,	"y":0.12757}
	,{"x":23,	"y":0.2913}
	,{"x":24,	"y":0.32964}
	,{"x":25,	"y":0.17745}
	,{"x":26,	"y":0.041332}
	,{"x":27,	"y":0.0018499}
	,{"x":28,	"y":4.2277e-5}
	,{"x":29,	"y":4.9779e-7}
	,{"x":30,	"y":3.1074e-9}
	,{"x":31,	"y":8.1912e-12}
	,{"x":32,	"y":1.2562e-14}
	,{"x":33,	"y":6.9868e-18}
	,{"x":34,	"y":2.2536e-21}
	,{"x":35,	"y":4.6873e-30}
	,{"x":36,	"y":2.9734e-39}
	,{"x":37,	"y":0}
	,{"x":38,	"y":0}
	,{"x":39,	"y":0}
	,{"x":40,	"y":0}
	,{"x":41,	"y":0}
	,{"x":42,	"y":0}
	,{"x":43,	"y":0}
	,{"x":44,	"y":0}
      ]
    }
    ,{
      "ifunc":15,
      "fName":"Te =    310.0 eV",
      "lx":45,
      "i0x":0,
      "i1x":44,
      "pts":[
	 {"x":0,	"y":0}
	,{"x":1,	"y":0}
	,{"x":2,	"y":0}
	,{"x":3,	"y":0}
	,{"x":4,	"y":0}
	,{"x":5,	"y":0}
	,{"x":6,	"y":4.2039e-45}
	,{"x":7,	"y":2.69554e-41}
	,{"x":8,	"y":1.0528e-37}
	,{"x":9,	"y":3.5389e-34}
	,{"x":10,	"y":7.1028e-31}
	,{"x":11,	"y":9.8741e-28}
	,{"x":12,	"y":9.3962e-25}
	,{"x":13,	"y":5.7325e-22}
	,{"x":14,	"y":1.0383e-19}
	,{"x":15,	"y":2.0475e-17}
	,{"x":16,	"y":4.2419e-14}
	,{"x":17,	"y":3.0205e-11}
	,{"x":18,	"y":8.328e-9}
	,{"x":19,	"y":9.5549e-7}
	,{"x":20,	"y":4.859e-5}
	,{"x":21,	"y":0.0011356}
	,{"x":22,	"y":0.012863}
	,{"x":23,	"y":0.075406}
	,{"x":24,	"y":0.2345}
	,{"x":25,	"y":0.37326}
	,{"x":26,	"y":0.25313}
	,{"x":27,	"y":0.044953}
	,{"x":28,	"y":0.0044446}
	,{"x":29,	"y":0.00024745}
	,{"x":30,	"y":7.8191e-6}
	,{"x":31,	"y":1.1974e-7}
	,{"x":32,	"y":1.1393e-9}
	,{"x":33,	"y":4.8255e-12}
	,{"x":34,	"y":1.1765e-14}
	,{"x":35,	"y":2.8222e-21}
	,{"x":36,	"y":2.5763e-28}
	,{"x":37,	"y":9.2104e-36}
	,{"x":38,	"y":1.52742e-43}
	,{"x":39,	"y":0}
	,{"x":40,	"y":0}
	,{"x":41,	"y":0}
	,{"x":42,	"y":0}
	,{"x":43,	"y":0}
	,{"x":44,	"y":0}
      ]
    }
    ,{
      "ifunc":16,
      "fName":"Te =    390.0 eV",
      "lx":45,
      "i0x":0,
      "i1x":44,
      "pts":[
	 {"x":0,	"y":0}
	,{"x":1,	"y":0}
	,{"x":2,	"y":0}
	,{"x":3,	"y":0}
	,{"x":4,	"y":0}
	,{"x":5,	"y":0}
	,{"x":6,	"y":0}
	,{"x":7,	"y":1.4013e-45}
	,{"x":8,	"y":9.98285e-42}
	,{"x":9,	"y":4.713e-38}
	,{"x":10,	"y":1.3379e-34}
	,{"x":11,	"y":2.658e-31}
	,{"x":12,	"y":3.6671e-28}
	,{"x":13,	"y":3.3283e-25}
	,{"x":14,	"y":9.6622e-23}
	,{"x":15,	"y":2.9069e-20}
	,{"x":16,	"y":1.0007e-16}
	,{"x":17,	"y":1.2309e-13}
	,{"x":18,	"y":6.055e-11}
	,{"x":19,	"y":1.2785e-8}
	,{"x":20,	"y":1.2252e-6}
	,{"x":21,	"y":5.4804e-5}
	,{"x":22,	"y":0.0012026}
	,{"x":23,	"y":0.013836}
	,{"x":24,	"y":0.086799}
	,{"x":25,	"y":0.28345}
	,{"x":26,	"y":0.38845}
	,{"x":27,	"y":0.17295}
	,{"x":28,	"y":0.045465}
	,{"x":29,	"y":0.0071068}
	,{"x":30,	"y":0.00065728}
	,{"x":31,	"y":3.2323e-5}
	,{"x":32,	"y":1.0286e-6}
	,{"x":33,	"y":1.6629e-8}
	,{"x":34,	"y":1.4704e-10}
	,{"x":35,	"y":7.083e-16}
	,{"x":36,	"y":1.5142e-21}
	,{"x":37,	"y":1.4813e-27}
	,{"x":38,	"y":7.8753e-34}
	,{"x":39,	"y":1.1848e-40}
	,{"x":40,	"y":0}
	,{"x":41,	"y":0}
	,{"x":42,	"y":0}
	,{"x":43,	"y":0}
	,{"x":44,	"y":0}
      ]
    }
    ,{
      "ifunc":17,
      "fName":"Te =    475.0 eV",
      "lx":45,
      "i0x":0,
      "i1x":44,
      "pts":[
	 {"x":0,	"y":0}
	,{"x":1,	"y":0}
	,{"x":2,	"y":0}
	,{"x":3,	"y":0}
	,{"x":4,	"y":0}
	,{"x":5,	"y":0}
	,{"x":6,	"y":0}
	,{"x":7,	"y":0}
	,{"x":8,	"y":5.60519e-45}
	,{"x":9,	"y":3.30973e-41}
	,{"x":10,	"y":1.2289e-37}
	,{"x":11,	"y":3.2179e-34}
	,{"x":12,	"y":5.9054e-31}
	,{"x":13,	"y":7.3084e-28}
	,{"x":14,	"y":3.0739e-25}
	,{"x":15,	"y":1.294e-22}
	,{"x":16,	"y":6.4327e-19}
	,{"x":17,	"y":1.1849e-15}
	,{"x":18,	"y":9.0115e-13}
	,{"x":19,	"y":3.0113e-10}
	,{"x":20,	"y":4.6554e-8}
	,{"x":21,	"y":3.423e-6}
	,{"x":22,	"y":0.00012473}
	,{"x":23,	"y":0.0024084}
	,{"x":24,	"y":0.025722}
	,{"x":25,	"y":0.14263}
	,{"x":26,	"y":0.32853}
	,{"x":27,	"y":0.28616}
	,{"x":28,	"y":0.15267}
	,{"x":29,	"y":0.050348}
	,{"x":30,	"y":0.010152}
	,{"x":31,	"y":0.0011624}
	,{"x":32,	"y":8.8387e-5}
	,{"x":33,	"y":3.7238e-6}
	,{"x":34,	"y":8.1402e-8}
	,{"x":35,	"y":3.106e-12}
	,{"x":36,	"y":5.8771e-17}
	,{"x":37,	"y":5.6952e-22}
	,{"x":38,	"y":3.3352e-27}
	,{"x":39,	"y":6.7226e-33}
	,{"x":40,	"y":7.0131e-39}
	,{"x":41,	"y":1.4013e-45}
	,{"x":42,	"y":0}
	,{"x":43,	"y":0}
	,{"x":44,	"y":0}
      ]
    }
    ,{
      "ifunc":18,
      "fName":"Te =    655.0 eV",
      "lx":45,
      "i0x":0,
      "i1x":44,
      "pts":[
	 {"x":0,	"y":0}
	,{"x":1,	"y":0}
	,{"x":2,	"y":0}
	,{"x":3,	"y":0}
	,{"x":4,	"y":0}
	,{"x":5,	"y":0}
	,{"x":6,	"y":0}
	,{"x":7,	"y":0}
	,{"x":8,	"y":0}
	,{"x":9,	"y":0}
	,{"x":10,	"y":1.98844e-42}
	,{"x":11,	"y":7.8183e-39}
	,{"x":12,	"y":2.1741e-35}
	,{"x":13,	"y":4.2502e-32}
	,{"x":14,	"y":3.0925e-29}
	,{"x":15,	"y":2.1612e-26}
	,{"x":16,	"y":1.7594e-22}
	,{"x":17,	"y":5.6452e-19}
	,{"x":18,	"y":7.8428e-16}
	,{"x":19,	"y":4.9825e-13}
	,{"x":20,	"y":1.5141e-10}
	,{"x":21,	"y":2.2466e-8}
	,{"x":22,	"y":1.687e-6}
	,{"x":23,	"y":6.8246e-5}
	,{"x":24,	"y":0.0015507}
	,{"x":25,	"y":0.01813}
	,{"x":26,	"y":0.086423}
	,{"x":27,	"y":0.18759}
	,{"x":28,	"y":0.26308}
	,{"x":29,	"y":0.23989}
	,{"x":30,	"y":0.13917}
	,{"x":31,	"y":0.049867}
	,{"x":32,	"y":0.012262}
	,{"x":33,	"y":0.0018387}
	,{"x":34,	"y":0.00013111}
	,{"x":35,	"y":6.9495e-8}
	,{"x":36,	"y":2.1065e-11}
	,{"x":37,	"y":3.7855e-15}
	,{"x":38,	"y":4.6296e-19}
	,{"x":39,	"y":2.5171e-23}
	,{"x":40,	"y":8.3882e-28}
	,{"x":41,	"y":6.5852e-33}
	,{"x":42,	"y":4.3576e-38}
	,{"x":43,	"y":0}
	,{"x":44,	"y":0}
      ]
    }
    ,{
      "ifunc":19,
      "fName":"Te =    845.0 eV",
      "lx":45,
      "i0x":0,
      "i1x":44,
      "pts":[
	 {"x":0,	"y":0}
	,{"x":1,	"y":0}
	,{"x":2,	"y":0}
	,{"x":3,	"y":0}
	,{"x":4,	"y":0}
	,{"x":5,	"y":0}
	,{"x":6,	"y":0}
	,{"x":7,	"y":0}
	,{"x":8,	"y":0}
	,{"x":9,	"y":0}
	,{"x":10,	"y":0}
	,{"x":11,	"y":1.73761e-42}
	,{"x":12,	"y":6.5165e-39}
	,{"x":13,	"y":1.7717e-35}
	,{"x":14,	"y":1.9126e-32}
	,{"x":15,	"y":1.9421e-29}
	,{"x":16,	"y":2.1815e-25}
	,{"x":17,	"y":1.012e-21}
	,{"x":18,	"y":2.104e-18}
	,{"x":19,	"y":2.0611e-15}
	,{"x":20,	"y":9.9063e-13}
	,{"x":21,	"y":2.3737e-10}
	,{"x":22,	"y":2.9258e-8}
	,{"x":23,	"y":1.9696e-6}
	,{"x":24,	"y":7.5276e-5}
	,{"x":25,	"y":0.001476}
	,{"x":26,	"y":0.011695}
	,{"x":27,	"y":0.046617}
	,{"x":28,	"y":0.12374}
	,{"x":29,	"y":0.22058}
	,{"x":30,	"y":0.25715}
	,{"x":31,	"y":0.19507}
	,{"x":32,	"y":0.10347}
	,{"x":33,	"y":0.034841}
	,{"x":34,	"y":0.0052835}
	,{"x":35,	"y":1.3994e-5}
	,{"x":36,	"y":2.2991e-8}
	,{"x":37,	"y":2.4454e-11}
	,{"x":38,	"y":1.8881e-14}
	,{"x":39,	"y":7.5466e-18}
	,{"x":40,	"y":2.0392e-21}
	,{"x":41,	"y":1.6205e-25}
	,{"x":42,	"y":1.1966e-29}
	,{"x":43,	"y":4.2039e-45}
	,{"x":44,	"y":0}
      ]
    }
    ,{
      "ifunc":20,
      "fName":"Te =   1000.0 eV",
      "lx":45,
      "i0x":0,
      "i1x":44,
      "pts":[
	 {"x":0,	"y":0}
	,{"x":1,	"y":0}
	,{"x":2,	"y":0}
	,{"x":3,	"y":0}
	,{"x":4,	"y":0}
	,{"x":5,	"y":0}
	,{"x":6,	"y":0}
	,{"x":7,	"y":0}
	,{"x":8,	"y":0}
	,{"x":9,	"y":0}
	,{"x":10,	"y":0}
	,{"x":11,	"y":7.00649e-45}
	,{"x":12,	"y":2.90573e-41}
	,{"x":13,	"y":9.7173e-38}
	,{"x":14,	"y":1.3392e-34}
	,{"x":15,	"y":1.7223e-31}
	,{"x":16,	"y":2.3371e-27}
	,{"x":17,	"y":1.3471e-23}
	,{"x":18,	"y":3.5564e-20}
	,{"x":19,	"y":4.5068e-17}
	,{"x":20,	"y":2.8452e-14}
	,{"x":21,	"y":9.0748e-12}
	,{"x":22,	"y":1.5056e-9}
	,{"x":23,	"y":1.3764e-7}
	,{"x":24,	"y":7.1931e-6}
	,{"x":25,	"y":0.00019323}
	,{"x":26,	"y":0.0020908}
	,{"x":27,	"y":0.01196}
	,{"x":28,	"y":0.046379}
	,{"x":29,	"y":0.12275}
	,{"x":30,	"y":0.21533}
	,{"x":31,	"y":0.25285}
	,{"x":32,	"y":0.20977}
	,{"x":33,	"y":0.1122}
	,{"x":34,	"y":0.026294}
	,{"x":35,	"y":0.00017023}
	,{"x":36,	"y":7.146e-7}
	,{"x":37,	"y":2.0337e-9}
	,{"x":38,	"y":4.3271e-12}
	,{"x":39,	"y":5.1618e-15}
	,{"x":40,	"y":4.3766e-18}
	,{"x":41,	"y":1.2234e-21}
	,{"x":42,	"y":3.4016e-25}
	,{"x":43,	"y":1.7412e-38}
	,{"x":44,	"y":0}
      ]
    }
    ,{
      "ifunc":21,
      "fName":"Te =   1441.0 eV",
      "lx":45,
      "i0x":0,
      "i1x":44,
      "pts":[
	 {"x":0,	"y":0}
	,{"x":1,	"y":0}
	,{"x":2,	"y":0}
	,{"x":3,	"y":0}
	,{"x":4,	"y":0}
	,{"x":5,	"y":0}
	,{"x":6,	"y":0}
	,{"x":7,	"y":0}
	,{"x":8,	"y":0}
	,{"x":9,	"y":0}
	,{"x":10,	"y":0}
	,{"x":11,	"y":0}
	,{"x":12,	"y":0}
	,{"x":13,	"y":1.25416e-42}
	,{"x":14,	"y":2.8304e-39}
	,{"x":15,	"y":5.9236e-36}
	,{"x":16,	"y":1.1573e-31}
	,{"x":17,	"y":1.0155e-27}
	,{"x":18,	"y":4.2468e-24}
	,{"x":19,	"y":8.8487e-21}
	,{"x":20,	"y":9.4724e-18}
	,{"x":21,	"y":5.2686e-15}
	,{"x":22,	"y":1.5586e-12}
	,{"x":23,	"y":2.5869e-10}
	,{"x":24,	"y":2.4922e-8}
	,{"x":25,	"y":1.2484e-6}
	,{"x":26,	"y":2.526e-5}
	,{"x":27,	"y":0.00029213}
	,{"x":28,	"y":0.0023541}
	,{"x":29,	"y":0.013325}
	,{"x":30,	"y":0.051404}
	,{"x":31,	"y":0.13891}
	,{"x":32,	"y":0.2683}
	,{"x":33,	"y":0.33882}
	,{"x":34,	"y":0.18067}
	,{"x":35,	"y":0.0057722}
	,{"x":36,	"y":0.00012838}
	,{"x":37,	"y":2.0848e-6}
	,{"x":38,	"y":2.6558e-8}
	,{"x":39,	"y":2.1615e-10}
	,{"x":40,	"y":1.3521e-12}
	,{"x":41,	"y":3.2269e-15}
	,{"x":42,	"y":8.9998e-18}
	,{"x":43,	"y":2.0983e-27}
	,{"x":44,	"y":9.0017e-38}
      ]
    }
    ,{
      "ifunc":22,
      "fName":"Te =   1925.0 eV",
      "lx":45,
      "i0x":0,
      "i1x":44,
      "pts":[
	 {"x":0,	"y":0}
	,{"x":1,	"y":0}
	,{"x":2,	"y":0}
	,{"x":3,	"y":0}
	,{"x":4,	"y":0}
	,{"x":5,	"y":0}
	,{"x":6,	"y":0}
	,{"x":7,	"y":0}
	,{"x":8,	"y":0}
	,{"x":9,	"y":0}
	,{"x":10,	"y":0}
	,{"x":11,	"y":0}
	,{"x":12,	"y":0}
	,{"x":13,	"y":0}
	,{"x":14,	"y":7.13261e-43}
	,{"x":15,	"y":2.1582e-39}
	,{"x":16,	"y":5.4833e-35}
	,{"x":17,	"y":6.4719e-31}
	,{"x":18,	"y":3.7463e-27}
	,{"x":19,	"y":1.1092e-23}
	,{"x":20,	"y":1.7241e-20}
	,{"x":21,	"y":1.4216e-17}
	,{"x":22,	"y":6.336e-15}
	,{"x":23,	"y":1.6065e-12}
	,{"x":24,	"y":2.3919e-10}
	,{"x":25,	"y":1.8775e-8}
	,{"x":26,	"y":6.0063e-7}
	,{"x":27,	"y":1.1454e-5}
	,{"x":28,	"y":0.00015476}
	,{"x":29,	"y":0.0014953}
	,{"x":30,	"y":0.010013}
	,{"x":31,	"y":0.048267}
	,{"x":32,	"y":0.16734}
	,{"x":33,	"y":0.37969}
	,{"x":34,	"y":0.35897}
	,{"x":35,	"y":0.031896}
	,{"x":36,	"y":0.0020548}
	,{"x":37,	"y":0.00010058}
	,{"x":38,	"y":3.9521e-6}
	,{"x":39,	"y":1.0667e-7}
	,{"x":40,	"y":2.2993e-9}
	,{"x":41,	"y":1.9439e-11}
	,{"x":42,	"y":2.211e-13}
	,{"x":43,	"y":6.9009e-21}
	,{"x":44,	"y":4.5582e-29}
      ]
    }
    ,{
      "ifunc":23,
      "fName":"Te =   2454.0 eV",
      "lx":45,
      "i0x":0,
      "i1x":44,
      "pts":[
	 {"x":0,	"y":0}
	,{"x":1,	"y":0}
	,{"x":2,	"y":0}
	,{"x":3,	"y":0}
	,{"x":4,	"y":0}
	,{"x":5,	"y":0}
	,{"x":6,	"y":0}
	,{"x":7,	"y":0}
	,{"x":8,	"y":0}
	,{"x":9,	"y":0}
	,{"x":10,	"y":0}
	,{"x":11,	"y":0}
	,{"x":12,	"y":0}
	,{"x":13,	"y":0}
	,{"x":14,	"y":0}
	,{"x":15,	"y":3.46401e-42}
	,{"x":16,	"y":1.0842e-37}
	,{"x":17,	"y":1.6202e-33}
	,{"x":18,	"y":1.2105e-29}
	,{"x":19,	"y":4.713e-26}
	,{"x":20,	"y":9.8045e-23}
	,{"x":21,	"y":1.0972e-19}
	,{"x":22,	"y":6.7393e-17}
	,{"x":23,	"y":2.3808e-14}
	,{"x":24,	"y":4.9809e-12}
	,{"x":25,	"y":5.5693e-10}
	,{"x":26,	"y":2.5626e-8}
	,{"x":27,	"y":7.2227e-7}
	,{"x":28,	"y":1.4596e-5}
	,{"x":29,	"y":0.00021354}
	,{"x":30,	"y":0.0021946}
	,{"x":31,	"y":0.016507}
	,{"x":32,	"y":0.089786}
	,{"x":33,	"y":0.31916}
	,{"x":34,	"y":0.47082}
	,{"x":35,	"y":0.087708}
	,{"x":36,	"y":0.012161}
	,{"x":37,	"y":0.0013152}
	,{"x":38,	"y":0.00011561}
	,{"x":39,	"y":7.2906e-6}
	,{"x":40,	"y":3.7576e-7}
	,{"x":41,	"y":7.3865e-9}
	,{"x":42,	"y":2.2049e-10}
	,{"x":43,	"y":1.7033e-16}
	,{"x":44,	"y":3.0458e-23}
      ]
    }
    ,{
      "ifunc":24,
      "fName":"Te =   3030.0 eV",
      "lx":45,
      "i0x":0,
      "i1x":44,
      "pts":[
	 {"x":0,	"y":0}
	,{"x":1,	"y":0}
	,{"x":2,	"y":0}
	,{"x":3,	"y":0}
	,{"x":4,	"y":0}
	,{"x":5,	"y":0}
	,{"x":6,	"y":0}
	,{"x":7,	"y":0}
	,{"x":8,	"y":0}
	,{"x":9,	"y":0}
	,{"x":10,	"y":0}
	,{"x":11,	"y":0}
	,{"x":12,	"y":0}
	,{"x":13,	"y":0}
	,{"x":14,	"y":0}
	,{"x":15,	"y":1.4013e-44}
	,{"x":16,	"y":5.3971e-40}
	,{"x":17,	"y":9.7808e-36}
	,{"x":18,	"y":9.0278e-32}
	,{"x":19,	"y":4.414e-28}
	,{"x":20,	"y":1.1693e-24}
	,{"x":21,	"y":1.6869e-21}
	,{"x":22,	"y":1.3498e-18}
	,{"x":23,	"y":6.2677e-16}
	,{"x":24,	"y":1.7382e-13}
	,{"x":25,	"y":2.6061e-11}
	,{"x":26,	"y":1.6229e-9}
	,{"x":27,	"y":6.3126e-8}
	,{"x":28,	"y":1.7787e-6}
	,{"x":29,	"y":3.6627e-5}
	,{"x":30,	"y":0.00053476}
	,{"x":31,	"y":0.0057921}
	,{"x":32,	"y":0.045519}
	,{"x":33,	"y":0.23363}
	,{"x":34,	"y":0.49807}
	,{"x":35,	"y":0.16514}
	,{"x":36,	"y":0.041482}
	,{"x":37,	"y":0.0082626}
	,{"x":38,	"y":0.0013484}
	,{"x":39,	"y":0.00016285}
	,{"x":40,	"y":1.628e-5}
	,{"x":41,	"y":5.8988e-7}
	,{"x":42,	"y":3.598e-8}
	,{"x":43,	"y":2.6821e-13}
	,{"x":44,	"y":4.9193e-19}
      ]
    }
    ,{
      "ifunc":25,
      "fName":"Te =   3655.0 eV",
      "lx":45,
      "i0x":0,
      "i1x":44,
      "pts":[
	 {"x":0,	"y":0}
	,{"x":1,	"y":0}
	,{"x":2,	"y":0}
	,{"x":3,	"y":0}
	,{"x":4,	"y":0}
	,{"x":5,	"y":0}
	,{"x":6,	"y":0}
	,{"x":7,	"y":0}
	,{"x":8,	"y":0}
	,{"x":9,	"y":0}
	,{"x":10,	"y":0}
	,{"x":11,	"y":0}
	,{"x":12,	"y":0}
	,{"x":13,	"y":0}
	,{"x":14,	"y":0}
	,{"x":15,	"y":0}
	,{"x":16,	"y":4.88773e-42}
	,{"x":17,	"y":1.0526e-37}
	,{"x":18,	"y":1.1689e-33}
	,{"x":19,	"y":6.9432e-30}
	,{"x":20,	"y":2.2541e-26}
	,{"x":21,	"y":4.043e-23}
	,{"x":22,	"y":4.0638e-20}
	,{"x":23,	"y":2.389e-17}
	,{"x":24,	"y":8.4362e-15}
	,{"x":25,	"y":1.6279e-12}
	,{"x":26,	"y":1.3165e-10}
	,{"x":27,	"y":6.7458e-9}
	,{"x":28,	"y":2.5238e-7}
	,{"x":29,	"y":6.9618e-6}
	,{"x":30,	"y":0.00013729}
	,{"x":31,	"y":0.0020261}
	,{"x":32,	"y":0.021777}
	,{"x":33,	"y":0.15295}
	,{"x":34,	"y":0.4472}
	,{"x":35,	"y":0.23709}
	,{"x":36,	"y":0.096619}
	,{"x":37,	"y":0.03162}
	,{"x":38,	"y":0.0085214}
	,{"x":39,	"y":0.0017343}
	,{"x":40,	"y":0.0002943}
	,{"x":41,	"y":1.7055e-5}
	,{"x":42,	"y":1.8159e-6}
	,{"x":43,	"y":7.3396e-11}
	,{"x":44,	"y":7.6344e-16}
      ]
    }
    ,{
      "ifunc":26,
      "fName":"Te =   4331.0 eV",
      "lx":45,
      "i0x":0,
      "i1x":44,
      "pts":[
	 {"x":0,	"y":0}
	,{"x":1,	"y":0}
	,{"x":2,	"y":0}
	,{"x":3,	"y":0}
	,{"x":4,	"y":0}
	,{"x":5,	"y":0}
	,{"x":6,	"y":0}
	,{"x":7,	"y":0}
	,{"x":8,	"y":0}
	,{"x":9,	"y":0}
	,{"x":10,	"y":0}
	,{"x":11,	"y":0}
	,{"x":12,	"y":0}
	,{"x":13,	"y":0}
	,{"x":14,	"y":0}
	,{"x":15,	"y":0}
	,{"x":16,	"y":6.5861e-44}
	,{"x":17,	"y":1.634e-39}
	,{"x":18,	"y":2.1283e-35}
	,{"x":19,	"y":1.5023e-31}
	,{"x":20,	"y":5.8682e-28}
	,{"x":21,	"y":1.2756e-24}
	,{"x":22,	"y":1.5626e-21}
	,{"x":23,	"y":1.1268e-18}
	,{"x":24,	"y":4.9276e-16}
	,{"x":25,	"y":1.1893e-13}
	,{"x":26,	"y":1.2122e-11}
	,{"x":27,	"y":7.9219e-10}
	,{"x":28,	"y":3.8045e-8}
	,{"x":29,	"y":1.3555e-6}
	,{"x":30,	"y":3.4755e-5}
	,{"x":31,	"y":0.00067246}
	,{"x":32,	"y":0.0095139}
	,{"x":33,	"y":0.088008}
	,{"x":34,	"y":0.34031}
	,{"x":35,	"y":0.26848}
	,{"x":36,	"y":0.16434}
	,{"x":37,	"y":0.081606}
	,{"x":38,	"y":0.033468}
	,{"x":39,	"y":0.010514}
	,{"x":40,	"y":0.0027702}
	,{"x":41,	"y":0.00023431}
	,{"x":42,	"y":3.9205e-5}
	,{"x":43,	"y":5.8714e-9}
	,{"x":44,	"y":2.3422e-13}
      ]
    }
    ,{
      "ifunc":27,
      "fName":"Te =   5060.0 eV",
      "lx":45,
      "i0x":0,
      "i1x":44,
      "pts":[
	 {"x":0,	"y":0}
	,{"x":1,	"y":0}
	,{"x":2,	"y":0}
	,{"x":3,	"y":0}
	,{"x":4,	"y":0}
	,{"x":5,	"y":0}
	,{"x":6,	"y":0}
	,{"x":7,	"y":0}
	,{"x":8,	"y":0}
	,{"x":9,	"y":0}
	,{"x":10,	"y":0}
	,{"x":11,	"y":0}
	,{"x":12,	"y":0}
	,{"x":13,	"y":0}
	,{"x":14,	"y":0}
	,{"x":15,	"y":0}
	,{"x":16,	"y":1.4013e-45}
	,{"x":17,	"y":3.13555e-41}
	,{"x":18,	"y":4.7575e-37}
	,{"x":19,	"y":3.9209e-33}
	,{"x":20,	"y":1.7975e-29}
	,{"x":21,	"y":4.6326e-26}
	,{"x":22,	"y":6.7949e-23}
	,{"x":23,	"y":5.9114e-20}
	,{"x":24,	"y":3.1295e-17}
	,{"x":25,	"y":9.2075e-15}
	,{"x":26,	"y":1.1555e-12}
	,{"x":27,	"y":9.3976e-11}
	,{"x":28,	"y":5.6443e-9}
	,{"x":29,	"y":2.5269e-7}
	,{"x":30,	"y":8.1873e-6}
	,{"x":31,	"y":0.00020194}
	,{"x":32,	"y":0.0036521}
	,{"x":33,	"y":0.043206}
	,{"x":34,	"y":0.21467}
	,{"x":35,	"y":0.23879}
	,{"x":36,	"y":0.20791}
	,{"x":37,	"y":0.14759}
	,{"x":38,	"y":0.086949}
	,{"x":39,	"y":0.039677}
	,{"x":40,	"y":0.015165}
	,{"x":41,	"y":0.0017553}
	,{"x":42,	"y":0.00042828}
	,{"x":43,	"y":1.8236e-7}
	,{"x":44,	"y":2.1282e-11}
      ]
    }
    ,{
      "ifunc":28,
      "fName":"Te =   5844.0 eV",
      "lx":45,
      "i0x":0,
      "i1x":44,
      "pts":[
	 {"x":0,	"y":0}
	,{"x":1,	"y":0}
	,{"x":2,	"y":0}
	,{"x":3,	"y":0}
	,{"x":4,	"y":0}
	,{"x":5,	"y":0}
	,{"x":6,	"y":0}
	,{"x":7,	"y":0}
	,{"x":8,	"y":0}
	,{"x":9,	"y":0}
	,{"x":10,	"y":0}
	,{"x":11,	"y":0}
	,{"x":12,	"y":0}
	,{"x":13,	"y":0}
	,{"x":14,	"y":0}
	,{"x":15,	"y":0}
	,{"x":16,	"y":0}
	,{"x":17,	"y":6.45999e-43}
	,{"x":18,	"y":1.128e-38}
	,{"x":19,	"y":1.0815e-34}
	,{"x":20,	"y":5.8066e-31}
	,{"x":21,	"y":1.7539e-27}
	,{"x":22,	"y":3.0236e-24}
	,{"x":23,	"y":3.1136e-21}
	,{"x":24,	"y":1.9648e-18}
	,{"x":25,	"y":6.9555e-16}
	,{"x":26,	"y":1.0561e-13}
	,{"x":27,	"y":1.0454e-11}
	,{"x":28,	"y":7.6908e-10}
	,{"x":29,	"y":4.2493e-8}
	,{"x":30,	"y":1.711e-6}
	,{"x":31,	"y":5.2689e-5}
	,{"x":32,	"y":0.0011915}
	,{"x":33,	"y":0.017634}
	,{"x":34,	"y":0.11022}
	,{"x":35,	"y":0.16624}
	,{"x":36,	"y":0.19711}
	,{"x":37,	"y":0.19198}
	,{"x":38,	"y":0.15521}
	,{"x":39,	"y":0.098022}
	,{"x":40,	"y":0.051851}
	,{"x":41,	"y":0.0078442}
	,{"x":42,	"y":0.0026402}
	,{"x":43,	"y":2.6438e-6}
	,{"x":44,	"y":7.4287e-10}
      ]
    }
    ,{
      "ifunc":29,
      "fName":"Te =   6685.0 eV",
      "lx":45,
      "i0x":0,
      "i1x":44,
      "pts":[
	 {"x":0,	"y":0}
	,{"x":1,	"y":0}
	,{"x":2,	"y":0}
	,{"x":3,	"y":0}
	,{"x":4,	"y":0}
	,{"x":5,	"y":0}
	,{"x":6,	"y":0}
	,{"x":7,	"y":0}
	,{"x":8,	"y":0}
	,{"x":9,	"y":0}
	,{"x":10,	"y":0}
	,{"x":11,	"y":0}
	,{"x":12,	"y":0}
	,{"x":13,	"y":0}
	,{"x":14,	"y":0}
	,{"x":15,	"y":0}
	,{"x":16,	"y":0}
	,{"x":17,	"y":1.4013e-44}
	,{"x":18,	"y":2.8954e-40}
	,{"x":19,	"y":3.1677e-36}
	,{"x":20,	"y":1.9562e-32}
	,{"x":21,	"y":6.8584e-29}
	,{"x":22,	"y":1.3817e-25}
	,{"x":23,	"y":1.6638e-22}
	,{"x":24,	"y":1.2278e-19}
	,{"x":25,	"y":5.124e-17}
	,{"x":26,	"y":9.2723e-15}
	,{"x":27,	"y":1.1036e-12}
	,{"x":28,	"y":9.7944e-11}
	,{"x":29,	"y":6.5458e-9}
	,{"x":30,	"y":3.1994e-7}
	,{"x":31,	"y":1.2033e-5}
	,{"x":32,	"y":0.00033397}
	,{"x":33,	"y":0.006082}
	,{"x":34,	"y":0.046957}
	,{"x":35,	"y":0.09283}
	,{"x":36,	"y":0.14538}
	,{"x":37,	"y":0.18729}
	,{"x":38,	"y":0.20054}
	,{"x":39,	"y":0.16863}
	,{"x":40,	"y":0.11903}
	,{"x":41,	"y":0.022753}
	,{"x":42,	"y":0.010147}
	,{"x":43,	"y":2.0708e-5}
	,{"x":44,	"y":1.2106e-8}
      ]
    }
    ,{
      "ifunc":30,
      "fName":"Te =   7585.0 eV",
      "lx":45,
      "i0x":0,
      "i1x":44,
      "pts":[
	 {"x":0,	"y":0}
	,{"x":1,	"y":0}
	,{"x":2,	"y":0}
	,{"x":3,	"y":0}
	,{"x":4,	"y":0}
	,{"x":5,	"y":0}
	,{"x":6,	"y":0}
	,{"x":7,	"y":0}
	,{"x":8,	"y":0}
	,{"x":9,	"y":0}
	,{"x":10,	"y":0}
	,{"x":11,	"y":0}
	,{"x":12,	"y":0}
	,{"x":13,	"y":0}
	,{"x":14,	"y":0}
	,{"x":15,	"y":0}
	,{"x":16,	"y":0}
	,{"x":17,	"y":0}
	,{"x":18,	"y":7.96638e-42}
	,{"x":19,	"y":9.8274e-38}
	,{"x":20,	"y":6.8863e-34}
	,{"x":21,	"y":2.7588e-30}
	,{"x":22,	"y":6.3983e-27}
	,{"x":23,	"y":8.9328e-24}
	,{"x":24,	"y":7.6927e-21}
	,{"x":25,	"y":3.7569e-18}
	,{"x":26,	"y":7.9832e-16}
	,{"x":27,	"y":1.1222e-13}
	,{"x":28,	"y":1.183e-11}
	,{"x":29,	"y":9.4471e-10}
	,{"x":30,	"y":5.5488e-8}
	,{"x":31,	"y":2.5177e-6}
	,{"x":32,	"y":8.4407e-5}
	,{"x":33,	"y":0.0018579}
	,{"x":34,	"y":0.017438}
	,{"x":35,	"y":0.044045}
	,{"x":36,	"y":0.088592}
	,{"x":37,	"y":0.14728}
	,{"x":38,	"y":0.203}
	,{"x":39,	"y":0.22133}
	,{"x":40,	"y":0.20164}
	,{"x":41,	"y":0.047446}
	,{"x":42,	"y":0.027176}
	,{"x":43,	"y":0.00010162}
	,{"x":44,	"y":1.1052e-7}
      ]
    }
    ,{
      "ifunc":31,
      "fName":"Te =   8546.0 eV",
      "lx":45,
      "i0x":0,
      "i1x":44,
      "pts":[
	 {"x":0,	"y":0}
	,{"x":1,	"y":0}
	,{"x":2,	"y":0}
	,{"x":3,	"y":0}
	,{"x":4,	"y":0}
	,{"x":5,	"y":0}
	,{"x":6,	"y":0}
	,{"x":7,	"y":0}
	,{"x":8,	"y":0}
	,{"x":9,	"y":0}
	,{"x":10,	"y":0}
	,{"x":11,	"y":0}
	,{"x":12,	"y":0}
	,{"x":13,	"y":0}
	,{"x":14,	"y":0}
	,{"x":15,	"y":0}
	,{"x":16,	"y":0}
	,{"x":17,	"y":0}
	,{"x":18,	"y":2.46629e-43}
	,{"x":19,	"y":3.3998e-39}
	,{"x":20,	"y":2.6753e-35}
	,{"x":21,	"y":1.2106e-31}
	,{"x":22,	"y":3.1912e-28}
	,{"x":23,	"y":5.0939e-25}
	,{"x":24,	"y":5.0447e-22}
	,{"x":25,	"y":2.8555e-19}
	,{"x":26,	"y":7.0627e-17}
	,{"x":27,	"y":1.1578e-14}
	,{"x":28,	"y":1.4276e-12}
	,{"x":29,	"y":1.3408e-10}
	,{"x":30,	"y":9.3138e-9}
	,{"x":31,	"y":5.0273e-7}
	,{"x":32,	"y":2.0128e-5}
	,{"x":33,	"y":0.00053031}
	,{"x":34,	"y":0.0059794}
	,{"x":35,	"y":0.018929}
	,{"x":36,	"y":0.047871}
	,{"x":37,	"y":0.10029}
	,{"x":38,	"y":0.17428}
	,{"x":39,	"y":0.24035}
	,{"x":40,	"y":0.27672}
	,{"x":41,	"y":0.078515}
	,{"x":42,	"y":0.056153}
	,{"x":43,	"y":0.00035307}
	,{"x":44,	"y":6.55e-7}
      ]
    }
    ,{
      "ifunc":32,
      "fName":"Te =  10000.0 eV",
      "lx":45,
      "i0x":0,
      "i1x":44,
      "pts":[
	 {"x":0,	"y":0}
	,{"x":1,	"y":0}
	,{"x":2,	"y":0}
	,{"x":3,	"y":0}
	,{"x":4,	"y":0}
	,{"x":5,	"y":0}
	,{"x":6,	"y":0}
	,{"x":7,	"y":0}
	,{"x":8,	"y":0}
	,{"x":9,	"y":0}
	,{"x":10,	"y":0}
	,{"x":11,	"y":0}
	,{"x":12,	"y":0}
	,{"x":13,	"y":0}
	,{"x":14,	"y":0}
	,{"x":15,	"y":0}
	,{"x":16,	"y":0}
	,{"x":17,	"y":0}
	,{"x":18,	"y":2.8026e-45}
	,{"x":19,	"y":3.66524e-41}
	,{"x":20,	"y":3.369e-37}
	,{"x":21,	"y":1.7846e-33}
	,{"x":22,	"y":5.5362e-30}
	,{"x":23,	"y":1.0472e-26}
	,{"x":24,	"y":1.2373e-23}
	,{"x":25,	"y":8.4412e-21}
	,{"x":26,	"y":2.5487e-18}
	,{"x":27,	"y":5.1546e-16}
	,{"x":28,	"y":7.8806e-14}
	,{"x":29,	"y":9.1979e-12}
	,{"x":30,	"y":7.9591e-10}
	,{"x":31,	"y":5.3642e-8}
	,{"x":32,	"y":2.6946e-6}
	,{"x":33,	"y":8.9491e-5}
	,{"x":34,	"y":0.0012806}
	,{"x":35,	"y":0.0053949}
	,{"x":36,	"y":0.018233}
	,{"x":37,	"y":0.051246}
	,{"x":38,	"y":0.11962}
	,{"x":39,	"y":0.22162}
	,{"x":40,	"y":0.34243}
	,{"x":41,	"y":0.1227}
	,{"x":42,	"y":0.11602}
	,{"x":43,	"y":0.0013556}
	,{"x":44,	"y":4.7447e-6}
      ]
    }
    ,{
      "ifunc":33,
      "fName":"Te =  20000.0 eV",
      "lx":45,
      "i0x":0,
      "i1x":44,
      "pts":[
	 {"x":0,	"y":0}
	,{"x":1,	"y":0}
	,{"x":2,	"y":0}
	,{"x":3,	"y":0}
	,{"x":4,	"y":0}
	,{"x":5,	"y":0}
	,{"x":6,	"y":0}
	,{"x":7,	"y":0}
	,{"x":8,	"y":0}
	,{"x":9,	"y":0}
	,{"x":10,	"y":0}
	,{"x":11,	"y":0}
	,{"x":12,	"y":0}
	,{"x":13,	"y":0}
	,{"x":14,	"y":0}
	,{"x":15,	"y":0}
	,{"x":16,	"y":0}
	,{"x":17,	"y":0}
	,{"x":18,	"y":0}
	,{"x":19,	"y":0}
	,{"x":20,	"y":1.4013e-45}
	,{"x":21,	"y":1.11263e-41}
	,{"x":22,	"y":7.1354e-38}
	,{"x":23,	"y":2.8368e-34}
	,{"x":24,	"y":7.1746e-31}
	,{"x":25,	"y":1.0815e-27}
	,{"x":26,	"y":7.468e-25}
	,{"x":27,	"y":3.543e-22}
	,{"x":28,	"y":1.3019e-19}
	,{"x":29,	"y":3.7451e-17}
	,{"x":30,	"y":8.2082e-15}
	,{"x":31,	"y":1.4394e-12}
	,{"x":32,	"y":1.9184e-10}
	,{"x":33,	"y":1.7155e-8}
	,{"x":34,	"y":6.8021e-7}
	,{"x":35,	"y":9.182e-6}
	,{"x":36,	"y":9.975e-5}
	,{"x":37,	"y":0.00090387}
	,{"x":38,	"y":0.0067965}
	,{"x":39,	"y":0.040936}
	,{"x":40,	"y":0.20167}
	,{"x":41,	"y":0.18276}
	,{"x":42,	"y":0.51702}
	,{"x":43,	"y":0.048392}
	,{"x":44,	"y":0.0014087}
      ]
    }
    ,{
      "ifunc":34,
      "fName":"Te =  50000.0 eV",
      "lx":45,
      "i0x":0,
      "i1x":44,
      "pts":[
	 {"x":0,	"y":0}
	,{"x":1,	"y":0}
	,{"x":2,	"y":0}
	,{"x":3,	"y":0}
	,{"x":4,	"y":0}
	,{"x":5,	"y":0}
	,{"x":6,	"y":0}
	,{"x":7,	"y":0}
	,{"x":8,	"y":0}
	,{"x":9,	"y":0}
	,{"x":10,	"y":0}
	,{"x":11,	"y":0}
	,{"x":12,	"y":0}
	,{"x":13,	"y":0}
	,{"x":14,	"y":0}
	,{"x":15,	"y":0}
	,{"x":16,	"y":0}
	,{"x":17,	"y":0}
	,{"x":18,	"y":0}
	,{"x":19,	"y":0}
	,{"x":20,	"y":0}
	,{"x":21,	"y":0}
	,{"x":22,	"y":0}
	,{"x":23,	"y":2.8026e-44}
	,{"x":24,	"y":1.9556e-40}
	,{"x":25,	"y":8.381e-37}
	,{"x":26,	"y":1.714e-33}
	,{"x":27,	"y":2.4626e-30}
	,{"x":28,	"y":2.8069e-27}
	,{"x":29,	"y":2.5669e-24}
	,{"x":30,	"y":1.837e-21}
	,{"x":31,	"y":1.0775e-18}
	,{"x":32,	"y":4.9138e-16}
	,{"x":33,	"y":1.5348e-13}
	,{"x":34,	"y":2.1869e-11}
	,{"x":35,	"y":1.1341e-9}
	,{"x":36,	"y":4.7725e-8}
	,{"x":37,	"y":1.6729e-6}
	,{"x":38,	"y":4.8231e-5}
	,{"x":39,	"y":0.0011096}
	,{"x":40,	"y":0.020419}
	,{"x":41,	"y":0.055791}
	,{"x":42,	"y":0.55007}
	,{"x":43,	"y":0.31646}
	,{"x":44,	"y":0.056101}
      ]
    }
    ,{
      "ifunc":35,
      "fName":"Te = 100000.0 eV",
      "lx":45,
      "i0x":0,
      "i1x":44,
      "pts":[
	 {"x":0,	"y":0}
	,{"x":1,	"y":0}
	,{"x":2,	"y":0}
	,{"x":3,	"y":0}
	,{"x":4,	"y":0}
	,{"x":5,	"y":0}
	,{"x":6,	"y":0}
	,{"x":7,	"y":0}
	,{"x":8,	"y":0}
	,{"x":9,	"y":0}
	,{"x":10,	"y":0}
	,{"x":11,	"y":0}
	,{"x":12,	"y":0}
	,{"x":13,	"y":0}
	,{"x":14,	"y":0}
	,{"x":15,	"y":0}
	,{"x":16,	"y":0}
	,{"x":17,	"y":0}
	,{"x":18,	"y":0}
	,{"x":19,	"y":0}
	,{"x":20,	"y":0}
	,{"x":21,	"y":0}
	,{"x":22,	"y":0}
	,{"x":23,	"y":0}
	,{"x":24,	"y":0}
	,{"x":25,	"y":7.84727e-44}
	,{"x":26,	"y":3.85019e-40}
	,{"x":27,	"y":1.3522e-36}
	,{"x":28,	"y":3.8123e-33}
	,{"x":29,	"y":8.7218e-30}
	,{"x":30,	"y":1.58e-26}
	,{"x":31,	"y":2.3626e-23}
	,{"x":32,	"y":2.7625e-20}
	,{"x":33,	"y":2.2148e-17}
	,{"x":34,	"y":8.1729e-15}
	,{"x":35,	"y":1.1091e-12}
	,{"x":36,	"y":1.2166e-10}
	,{"x":37,	"y":1.1014e-8}
	,{"x":38,	"y":8.0832e-7}
	,{"x":39,	"y":4.6523e-5}
	,{"x":40,	"y":0.0020983}
	,{"x":41,	"y":0.012678}
	,{"x":42,	"y":0.2896}
	,{"x":43,	"y":0.4671}
	,{"x":44,	"y":0.22847}
      ]
    }
  ]
}
